{
  "node": {
    "e137b79e15f5f34a5b3fed6f3fbc8ce1e7620af9": {
      "workers": {
        "app/Profile/page": "(action-browser)/./node_modules/next/dist/build/webpack/loaders/next-flight-action-entry-loader.js?actions=%5B%5B%22%2FUsers%2Femannuel%2FDocuments%2FProjetinhos%2FGitHub%2FBank-2.0%2Fsrc%2Fapp%2FProfile%2Factions%2FupdateProfile.ts%22%2C%5B%22default%22%5D%5D%5D&__client_imported__=true!"
      },
      "layer": {
        "app/Profile/page": "action-browser"
      }
    },
    "1f9394ffaa5a89071502edf91eeb094d698ab20c": {
      "workers": {
        "app/Deposit/page": "(action-browser)/./node_modules/next/dist/build/webpack/loaders/next-flight-action-entry-loader.js?actions=%5B%5B%22%2FUsers%2Femannuel%2FDocuments%2FProjetinhos%2FGitHub%2FBank-2.0%2Fsrc%2Fapp%2FDeposit%2FActions%2Fdeposit.ts%22%2C%5B%22default%22%5D%5D%5D&__client_imported__=true!"
      },
      "layer": {
        "app/Deposit/page": "action-browser"
      }
    },
    "b8b0b1b25e49b2fc532b95af5fc3f22c1fef5c5d": {
      "workers": {
        "app/Transfer/page": "(action-browser)/./node_modules/next/dist/build/webpack/loaders/next-flight-action-entry-loader.js?actions=%5B%5B%22%2FUsers%2Femannuel%2FDocuments%2FProjetinhos%2FGitHub%2FBank-2.0%2Fsrc%2Fapp%2FTransfer%2FActions%2Ftransfer.ts%22%2C%5B%22default%22%5D%5D%5D&__client_imported__=true!"
      },
      "layer": {
        "app/Transfer/page": "action-browser"
      }
    },
    "37f1e121c4bf5a2865d9bce20d659ddbc97b4ae4": {
      "workers": {
        "app/CreditCard/page": "(action-browser)/./node_modules/next/dist/build/webpack/loaders/next-flight-action-entry-loader.js?actions=%5B%5B%22%2FUsers%2Femannuel%2FDocuments%2FProjetinhos%2FGitHub%2FBank-2.0%2Fsrc%2Fapp%2FCreditCard%2FActions%2FSolicityCard.tsx%22%2C%5B%22default%22%5D%5D%5D&__client_imported__=true!"
      },
      "layer": {
        "app/CreditCard/page": "action-browser"
      }
    },
    "28c03dceaaf7e3762d95380ace8dc89e4a0b1a81": {
      "workers": {
        "app/CreditCard/page": "(action-browser)/./node_modules/next/dist/build/webpack/loaders/next-flight-action-entry-loader.js?actions=%5B%5B%22%2FUsers%2Femannuel%2FDocuments%2FProjetinhos%2FGitHub%2FBank-2.0%2Fsrc%2Fapp%2FCreditCard%2FActions%2FSolicityCard.tsx%22%2C%5B%22default%22%5D%5D%5D&__client_imported__=true!"
      },
      "layer": {
        "app/CreditCard/page": "action-browser"
      }
    },
    "0f945063e74833f7b1cb24f51164b3b82418a142": {
      "workers": {
        "app/CreditCard/page": "(action-browser)/./node_modules/next/dist/build/webpack/loaders/next-flight-action-entry-loader.js?actions=%5B%5B%22%2FUsers%2Femannuel%2FDocuments%2FProjetinhos%2FGitHub%2FBank-2.0%2Fsrc%2Fapp%2FCreditCard%2FActions%2FSolicityCard.tsx%22%2C%5B%22default%22%5D%5D%5D&__client_imported__=true!"
      },
      "layer": {
        "app/CreditCard/page": "action-browser"
      }
    }
  },
  "edge": {},
  "encryptionKey": "SqWP1BHFLSdo8evO68c72S/1bTMxs1PA+rKuXQWaHl4="
}